jsondbupload/__init__.py
jsondbupload/jsondbupload.py
jsondbupload-1.3.dist-info/WHEEL
jsondbupload-1.3.dist-info/METADATA
jsondbupload-1.3.dist-info/RECORD
