Metadata-Version: 2.1
Name: jsondbupload
Version: 1.3
Summary: Insert records to relational database from json file
Home-page: https://github.com/pub12/jsondbupload
License: MIT
Author: pub12
Author-email: pubudu79@gmail.com
Requires-Python: >=3.8,<4.0
Classifier: License :: OSI Approved :: MIT License
Classifier: Programming Language :: Python :: 3
Classifier: Programming Language :: Python :: 3.10
Classifier: Programming Language :: Python :: 3.8
Classifier: Programming Language :: Python :: 3.9
Requires-Dist: jstyleson (>=0.0.2,<0.0.3)
